mkwind/__init__.py
mkwind/builder/__init__.py
mkwind/builder/base.py
mkwind/builder/daemon.py
mkwind/builder/settings.py
mkwind/builder/tests/__init__.py
mkwind/builder/tests/test_base.py
mkwind/builder/tests/test_daemon.py
mkwind/builder/tests/test_settings.py
mkwind/cli/__init__.py
mkwind/cli/build_one.py
mkwind/cli/builder.py
mkwind/cli/cycle.py
mkwind/cli/postprocess.py
mkwind/cli/runner.py
mkwind/cli/wind.py
mkwind/jobs/__init__.py
mkwind/jobs/daemon.py
mkwind/jobs/dirmanager.py
mkwind/jobs/tests/__init__.py
mkwind/jobs/tests/test_daemon.py
mkwind/jobs/tests/test_dirmanager.py
mkwind/postprocess/__init__.py
mkwind/postprocess/base.py
mkwind/postprocess/daemon.py
mkwind/postprocess/tests/__init__.py
mkwind/postprocess/tests/test_base.py
mkwind/postprocess/tests/test_daemon.py
mkwind/schedulers/__init__.py
mkwind/schedulers/base.py
mkwind/schedulers/local.py
mkwind/schedulers/lsf.py
mkwind/schedulers/pueue.py
mkwind/schedulers/sge.py
mkwind/schedulers/slurm.py
mkwind/schedulers/tests/__init__.py
mkwind/schedulers/tests/test_base.py
mkwind/schedulers/tests/test_lsf.py
mkwind/schedulers/tests/test_pueue.py
mkwind/schedulers/tests/test_sge.py
mkwind/schedulers/tests/test_slurm.py
mkwind/schedulers/tests/files/__init__.py
mkwind/schedulers/tests/files/pueue.json
mkwind/schedulers/tests/files/sge_qacct.txt
mkwind/schedulers/tests/files/sge_qstat_p.xml
mkwind/schedulers/tests/files/sge_qstat_r.xml
mkwind/templates/__init__.py
mkwind/templates/base.py
mkwind/templates/local.sh
mkwind/templates/lsf.sh
mkwind/templates/pueue.sh
mkwind/templates/sge.sh
mkwind/templates/slurm.sh
mkwind/templates/tests/__init__.py
mkwind/templates/tests/test_slurm.py
mkwind/tests/__init__.py
mkwind/tests/files/__init__.py
mkwind/tests/files/jobinfo.json
mkwind/tests/files/jobresults.json
mkwind/tests/files/settings.yaml
mkwind/tests/files/clusters/__init__.py
mkwind/tests/files/clusters/cluster1.yaml
mkwind/tests/files/clusters/recipe.yaml
mkwind/tests/files/clusters/cluster2/__init__.py
mkwind-25.11.3.dist-info/licenses/LICENSE
mkwind-25.11.3.dist-info/licenses/NOTICE
mkwind-25.11.3.dist-info/METADATA
mkwind-25.11.3.dist-info/WHEEL
mkwind-25.11.3.dist-info/entry_points.txt
mkwind-25.11.3.dist-info/top_level.txt
mkwind-25.11.3.dist-info/RECORD
