Metadata-Version: 2.4
Name: mkwind
Version: 25.11.3
Summary: mkwind is a job building/submission automator companion to mkite
Author-email: Daniel Schwalbe-Koda <dskoda@ucla.edu>
Keywords: workflow,materials-science
Requires-Python: >=3.8
License-File: LICENSE
License-File: NOTICE
Requires-Dist: click
Requires-Dist: pydantic>=2.0
Requires-Dist: freezegun
Requires-Dist: jinja2
Dynamic: license-file
